{
  "ㄱ": "s",
  "ㄲ": "zä",
  "ㄴ": "a",
  "ㄷ": "c",
  "ㄸ": "dä",
  "ㄹ": "f",
  "ㅁ": "ne",
  "ㅂ": "h",
  "ㅃ": "mä",
  "ㅅ": "e",
  "ㅆ": "s",
  "ㅇ": "z",
  "ㅈ": "p",
  "ㅉ": "kä",
  "ㅊ": "t",
  "ㅋ": "v",
  "ㅌ": "b",
  "ㅍ": "q",
  "ㅎ": "u",
  "ㅏ": "st",
  "ㅐ": "in",
  "ㅑ": "vo",
  "ㅒ": "te",
  "ㅓ": "uß",
  "ㅔ": "oß",
  "ㅕ": "yi",
  "ㅖ": "hi",
  "ㅗ": "von",
  "ㅘ": "kas",
  "ㅙ": "nai",
  "ㅚ": "nos",
  "ㅛ": "nu",
  "ㅜ": "ru",
  "ㅝ": "vu",
  "ㅞ": "sin",
  "ㅟ": "fin",
  "ㅠ": "fei",
  "ㅡ": "ni",
  "ㅢ": "ei",
  "ㅣ": "i",
  "": "",
  "ㄳ": "fön",
  "ㄵ": "nüs",
  "ㄶ": "häs",
  "ㄺ": "bön",
  "ㄻ": "küa",
  "ㄼ": "xan",
  "ㄽ": "jin",
  "ㄾ": "xon",
  "ㄿ": "öna",
  "ㅀ": "niü",
  "ㅄ": "äin"
}